{
  "updatedAt": "2026-07-05T17:04:31.342Z",
  "stats": {
    "maxMagnitude": 4.6,
    "aftershocks": 2,
    "deaths": 2954,
    "injured": 16000,
    "missing": 43251
  },
  "prov": {
    "maxMagnitude": {
      "seenAt": "2026-07-05T17:04:31.342Z",
      "source": "USGS",
      "url": "https://earthquake.usgs.gov/earthquakes/eventpage/us6000t8yf"
    },
    "aftershocks": {
      "seenAt": "2026-07-05T17:04:31.342Z",
      "source": "USGS",
      "url": "https://earthquake.usgs.gov/earthquakes/eventpage/us6000t8yf"
    },
    "deaths": {
      "seenAt": "2026-07-05T17:04:31.342Z",
      "source": "ONU/OCHA · ref. internacional (Wikipedia EN)",
      "url": "https://en.wikipedia.org/wiki/2026_Venezuela_earthquakes"
    },
    "injured": {
      "seenAt": "2026-07-05T17:04:31.342Z",
      "source": "ONU/OCHA · ref. internacional (Wikipedia EN)",
      "url": "https://en.wikipedia.org/wiki/2026_Venezuela_earthquakes"
    },
    "missing": {
      "seenAt": "2026-07-01T18:23:23.731Z",
      "source": "ONU/OCHA · ref. internacional (Wikipedia EN)",
      "url": "https://en.wikipedia.org/wiki/2026_Venezuela_earthquakes"
    }
  },
  "alt": {
    "deaths": {
      "value": 2954,
      "source": "Efecto Cocuyo",
      "url": "https://efectococuyo.com/la-humanidad/a-10-dias-del-doble-terremoto-se-han-registrado-2-954-fallecidos/",
      "seenAt": "2026-07-05T03:54:42.368Z"
    },
    "injured": {
      "value": 32038,
      "source": "Runrun.es",
      "url": "https://runrun.es/noticias/612709/27jun-asciende-a-1-430-la-cifra-de-fallecidos-por-doblete-sismico-en-venezuela/",
      "seenAt": "2026-06-27T19:14:37.075Z"
    },
    "missing": {
      "value": 157,
      "source": "Efecto Cocuyo",
      "url": "https://efectococuyo.com/la-humanidad/jorge-rodriguez-188-muertes-1-520-heridos-157-desaparecidos-terremotos/",
      "seenAt": "2026-06-26T12:13:21.411Z"
    }
  },
  "sources": {
    "usgs": 0,
    "reliefweb": 0,
    "press": 12,
    "wikipedia": 1,
    "funvisis": 20
  },
  "counts": {
    "updates": 8,
    "news": 12,
    "quakes": 500
  }
}
